{
    "titulo_clase": "titulo1",
    "tema":{
        "titulo_tema":"titulo del tema. Ejemplo: Alfabeto",
        "subtemas":[
            {
                "titulo":"subTema1",
                "contenido":[
                    ["p",{"class":"1", "titulo":"", "color":"rojo"},
                        {"contenido":"parrafo del subtema 1"}
                    ],
                    ["table",{"class":"", "titulo":"", "color":""}
                        ,{"tr":
                            [
                                [{"th":"tabla titulo"}],
                                [{"td":"contenido"}, {"td":"contenido"}],
                                [{"td":"contenido"}, {"td":"contenido"}, {"td":"contenido"}]
                            ]
                        }
                    ],
                    ["div",{"class":"", "titulo":"","color":""},
                        {"contenido":
                            [
                                ["p",{"class":"", "titulo":"", "color":""},
                                    {"contenido":"Subtema1, contenido div"}
                                ]
                            ]
                        }
                    ]
                ]
            },
            {
                "titulo":"subTema2",
                "contenido":[
                    ["p",{"class":"", "titulo":"", "color":""},
                        {"contenido":"Subtema2, contenido 1"}
                    ],
                    ["p",{"class":"", "titulo":"", "color":""},
                        {"contenido":"Subtema2, contenido 2"}
                    ],
                    ["p",{"class":"", "titulo":"", "color":""},
                        {"contenido":"Subtema2, contenido 3"}
                    ],
                    ["p",{"class":"", "titulo":"", "color":""},
                        {"contenido":"Subtema2, contenido 4"}
                    ]
                ]
            }
        ]
    }
}